hlogger/__init__.py
hlogger/api.py
hlogger/hlogger.py
hlogger-1.3.1.dist-info/LICENSE
hlogger-1.3.1.dist-info/METADATA
hlogger-1.3.1.dist-info/WHEEL
hlogger-1.3.1.dist-info/top_level.txt
hlogger-1.3.1.dist-info/RECORD
