Metadata-Version: 2.1
Name: hlogger
Version: 1.3.1
Summary: A logger utility for python application
Author-email: llChameleoNll <chameleon2318@gmail.com>
Project-URL: Repository, https://github.com/sChameleoNz/hlogger
Project-URL: Issues, https://github.com/sChameleoNz/hlogger/issues
Project-URL: Buy me a coffee, https://www.buymeacoffee.com/llhoyall
Keywords: logging,logger
Classifier: Programming Language :: Python :: 3
Classifier: Operating System :: OS Independent
Classifier: License :: OSI Approved :: MIT License
Requires-Python: >=3.7
License-File: LICENSE
